vicutils/__init__.py
vicutils/geometry/__init__.py
vicutils/geometry/geometry.py
vicutils/pdf/__init__.py
vicutils/pdf/pdf.py
vicutils/printBin/__init__.py
vicutils/printBin/printBin.py
vicutils-0.39.dist-info/METADATA
vicutils-0.39.dist-info/WHEEL
vicutils-0.39.dist-info/top_level.txt
vicutils-0.39.dist-info/RECORD
