Metadata-Version: 2.4
Name: vicutils
Version: 0.39
Summary: Utility functions for Python programming
Home-page: https://victorio-dev.github.io/PythonSolutions/
Author: Vic-Nas
Author-email: nasci.victorio@gmail.com
Project-URL: Documentation, https://victorio-dev.github.io/PythonSolutions/#vicutils
Project-URL: Source, https://github.com/Victorio-dev/PythonSolutions/tree/main/vicutils
Classifier: Programming Language :: Python :: 3
Classifier: License :: OSI Approved :: MIT License
Classifier: Operating System :: OS Independent
Requires-Python: >=3.6
Requires-Dist: PyMuPDF>=1.23.0
Requires-Dist: Pillow>=10.0.0
Dynamic: author
Dynamic: author-email
Dynamic: classifier
Dynamic: description
Dynamic: description-content-type
Dynamic: home-page
Dynamic: project-url
Dynamic: requires-dist
Dynamic: requires-python
Dynamic: summary
